[
    {
        "userName": "lgavendanoa",
        "password": "admin1",
        "id": 124564
    },
    {
        "userName": "hbgramirezp",
        "password": "admin2",
        "id": 4562131
    },
    {
        "userName": "plperezg",
        "password": "admin3",
        "id": 456231546554
    },
    {
        "userName": "spromeror",
        "password": "admin4",
        "id": 45652145654
    },
    {
        "userName": "jasantosf",
        "password": "admin5",
        "id": 4564211456
    }
]